LICENSE
setup.cfg
setup.py
tracer_spans.egg-info/PKG-INFO
tracer_spans.egg-info/SOURCES.txt
tracer_spans.egg-info/dependency_links.txt
tracer_spans.egg-info/requires.txt
tracer_spans.egg-info/top_level.txt
tracers_spans/tracers-spans.py